ruamel/yaml/split/__init__.py
ruamel.yaml.split-0.2.2.dist-info/LICENSE
ruamel.yaml.split-0.2.2.dist-info/METADATA
ruamel.yaml.split-0.2.2.dist-info/WHEEL
ruamel.yaml.split-0.2.2.dist-info/top_level.txt
ruamel.yaml.split-0.2.2.dist-info/RECORD
