Metadata-Version: 2.1
Name: ruamel.yaml.split
Version: 0.2.2
Summary: YAML document splitter, with iterator that returns document, start linenumber and optionally data
Home-page: https://sourceforge.net/p/ruamel-yaml-split/code/ci/default/tree
Author: Anthon van der Neut
Author-email: a.van.der.neut@ruamel.eu
License: Copyright Ruamel bvba 2007-2022
Keywords: yaml multi document split
Classifier: Development Status :: 4 - Beta
Classifier: Intended Audience :: Developers
Classifier: License :: Other/Proprietary License
Classifier: Operating System :: OS Independent
Classifier: Programming Language :: Python
Requires-Python: >=3
License-File: LICENSE
